elasticmapper/__init__.py
elasticmapper/mapper.py
elasticmapper/supported_orms.py
elasticmapper/orm_mappings/__init__.py
elasticmapper/orm_mappings/django_mapping.py
elasticmapper/orm_mappings/peewee_mapping.py
elasticmapper/orm_mappings/sqlalchemy_mapping.py
elasticmapper-1.0.0.dist-info/LICENSE
elasticmapper-1.0.0.dist-info/METADATA
elasticmapper-1.0.0.dist-info/WHEEL
elasticmapper-1.0.0.dist-info/top_level.txt
elasticmapper-1.0.0.dist-info/RECORD
