Metadata-Version: 2.1
Name: elasticmapper
Version: 1.0.0
Summary: Generating ElasticSearch mappings based on ORM's models
Author-email: ihatemilk <vyckluchi75@gmail.com>
License: MIT License
Project-URL: Homepage, https://github.com/nomilkinmyhome/elasticmapper
Project-URL: Bug Tracker, https://github.com/nomilkinmyhome/elasticmapper/issues
Classifier: Programming Language :: Python :: 3
Classifier: License :: OSI Approved :: MIT License
Classifier: Operating System :: OS Independent
Requires-Python: >=3.7
License-File: LICENSE
